Workbook

Sheet 📊 Overview
A1: Asset Category | B1: Total Items | C1: High Priority | D1: Medium Priority | E1: Low Priority | F1: Completed | G1: In Progress | H1: Not Started | I1: Completion % | J1: Notes
A2: A. Methodology & Frameworks | B2: =COUNTA(A_Methodology!A:A)-1 -> 14 | C2: =COUNTIF(A_Methodology!G:G,"High") -> 7 | D2: =COUNTIF(A_Methodology!G:G,"Medium") -> 7 | E2: =COUNTIF(A_Methodology!G:G,"Low") -> 0 | F2: =COUNTIF(A_Methodology!H:H,"Complete") -> 0 | G2: =COUNTIF(A_Methodology!H:H,"In Progress") -> 0 | H2: =COUNTIF(A_Methodology!H:H,"Not Started") -> 14 | I2: =IF(B2>0,F2/B2,0) -> 0
A3: B. Templates & Tools | B3: =COUNTA(B_Templates!A:A)-1 -> 33 | C3: =COUNTIF(B_Templates!G:G,"High") -> 15 | D3: =COUNTIF(B_Templates!G:G,"Medium") -> 18 | E3: =COUNTIF(B_Templates!G:G,"Low") -> 0 | F3: =COUNTIF(B_Templates!H:H,"Complete") -> 0 | G3: =COUNTIF(B_Templates!H:H,"In Progress") -> 0 | H3: =COUNTIF(B_Templates!H:H,"Not Started") -> 33 | I3: =IF(B3>0,F3/B3,0) -> 0
A4: C. Playbooks & Guides | B4: =COUNTA(C_Playbooks!A:A)-1 -> 17 | C4: =COUNTIF(C_Playbooks!G:G,"High") -> 9 | D4: =COUNTIF(C_Playbooks!G:G,"Medium") -> 7 | E4: =COUNTIF(C_Playbooks!G:G,"Low") -> 1 | F4: =COUNTIF(C_Playbooks!H:H,"Complete") -> 0 | G4: =COUNTIF(C_Playbooks!H:H,"In Progress") -> 0 | H4: =COUNTIF(C_Playbooks!H:H,"Not Started") -> 17 | I4: =IF(B4>0,F4/B4,0) -> 0
A5: D. Knowledge Assets | B5: =COUNTA(D_Knowledge!A:A)-1 -> 13 | C5: =COUNTIF(D_Knowledge!G:G,"High") -> 3 | D5: =COUNTIF(D_Knowledge!G:G,"Medium") -> 7 | E5: =COUNTIF(D_Knowledge!G:G,"Low") -> 3 | F5: =COUNTIF(D_Knowledge!H:H,"Complete") -> 0 | G5: =COUNTIF(D_Knowledge!H:H,"In Progress") -> 0 | H5: =COUNTIF(D_Knowledge!H:H,"Not Started") -> 13 | I5: =IF(B5>0,F5/B5,0) -> 0
A6: E. Sales & Marketing | B6: =COUNTA(E_Sales!A:A)-1 -> 14 | C6: =COUNTIF(E_Sales!G:G,"High") -> 8 | D6: =COUNTIF(E_Sales!G:G,"Medium") -> 4 | E6: =COUNTIF(E_Sales!G:G,"Low") -> 2 | F6: =COUNTIF(E_Sales!H:H,"Complete") -> 0 | G6: =COUNTIF(E_Sales!H:H,"In Progress") -> 0 | H6: =COUNTIF(E_Sales!H:H,"Not Started") -> 14 | I6: =IF(B6>0,F6/B6,0) -> 0
A7: F. Operations & Process | B7: =COUNTA(F_Operations!A:A)-1 -> 8 | C7: =COUNTIF(F_Operations!G:G,"High") -> 3 | D7: =COUNTIF(F_Operations!G:G,"Medium") -> 5 | E7: =COUNTIF(F_Operations!G:G,"Low") -> 0 | F7: =COUNTIF(F_Operations!H:H,"Complete") -> 0 | G7: =COUNTIF(F_Operations!H:H,"In Progress") -> 0 | H7: =COUNTIF(F_Operations!H:H,"Not Started") -> 8 | I7: =IF(B7>0,F7/B7,0) -> 0
A8: G. People & Capabilities | B8: =COUNTA(G_People!A:A)-1 -> 6 | C8: =COUNTIF(G_People!G:G,"High") -> 2 | D8: =COUNTIF(G_People!G:G,"Medium") -> 4 | E8: =COUNTIF(G_People!G:G,"Low") -> 0 | F8: =COUNTIF(G_People!H:H,"Complete") -> 0 | G8: =COUNTIF(G_People!H:H,"In Progress") -> 0 | H8: =COUNTIF(G_People!H:H,"Not Started") -> 6 | I8: =IF(B8>0,F8/B8,0) -> 0
A9: H. Supporting Systems | B9: =COUNTA(H_Systems!A:A)-1 -> 5 | C9: =COUNTIF(H_Systems!G:G,"High") -> 2 | D9: =COUNTIF(H_Systems!G:G,"Medium") -> 3 | E9: =COUNTIF(H_Systems!G:G,"Low") -> 0 | F9: =COUNTIF(H_Systems!H:H,"Complete") -> 0 | G9: =COUNTIF(H_Systems!H:H,"In Progress") -> 0 | H9: =COUNTIF(H_Systems!H:H,"Not Started") -> 5 | I9: =IF(B9>0,F9/B9,0) -> 0
A11: TOTAL | B11: =SUM(B2:B9) -> 110 | C11: =SUM(C2:C9) -> 49 | D11: =SUM(D2:D9) -> 55 | E11: =SUM(E2:E9) -> 6 | F11: =SUM(F2:F9) -> 0 | G11: =SUM(G2:G9) -> 0 | H11: =SUM(H2:H9) -> 110 | I11: =IF(B11>0,F11/B11,0) -> 0

Sheet A_Methodology
A1: ID | B1: Category | C1: Sub-Category | D1: Asset Name | E1: Description | F1: Key Contents Summary | G1: Priority | H1: Status | I1: Owner | J1: Est. Hours | K1: Target Date | L1: Related Service Pack | M1: Notes
A2: A1-1 | B2: A1. Core Methodology | C2: 5C Framework | D2: 5C Framework | E2: Proprietary framework for Enterprise AI Platform | F2: 철학/개념, 5개 C별 상세정의, 적용 시나리오, 성공지표 | G2: High | H2: Not Started | J2: 40 | L2: Enterprise AI Platform | M2: IP 자산
A3: A1-2 | B3: A1. Core Methodology | C3: Context Engineering | D3: Context Engineering Methodology | E3: Systematic approach to building semantic layers and knowledge graphs | F3: Context 정의/분류, Semantic Layer 방법론, Ontology 모델링, Lifecycle 관리 | G3: High | H3: Not Started | J3: 32 | L3: Enterprise AI Platform | M3: IP 자산
A4: A1-3 | B4: A1. Core Methodology | C4: Agent Orchestration | D4: Agent Orchestration Framework | E4: Multi-agent architecture patterns and coordination strategies | F4: Architecture 패턴, Communication Protocol, Memory Architecture, Tool Integration | G4: High | H4: Not Started | J4: 24 | L4: Enterprise AI Platform
A5: A2-1 | B5: A2. Assessment Frameworks | C5: Maturity Model | D5: AI Maturity Model | E5: 5-level maturity assessment framework | F5: 5단계 정의, 6개 차원, 차원별×레벨별 특성 매트릭스, 벤치마크 데이터 | G5: High | H5: Not Started | J5: 16 | L5: AI Strategy & Readiness
A6: A2-2 | B6: A2. Assessment Frameworks | C6: Use Case Priority | D6: Use Case Prioritization Framework | E6: Framework for evaluating and prioritizing AI use cases | F6: Prioritization Criteria, 측정방법, 매트릭스 해석, 분류체계 | G6: High | H6: Not Started | J6: 12 | L6: AI Strategy & Readiness
A7: A2-3 | B7: A2. Assessment Frameworks | C7: Risk Assessment | D7: Risk Assessment Framework | E7: Comprehensive AI risk identification and evaluation | F7: Risk Taxonomy, Likelihood×Impact 평가, Scoring, Heat Map, Mitigation Strategy | G7: Medium | H7: Not Started | J7: 16 | L7: AI Risk & Compliance
A8: A3-1 | B8: A3. Design Frameworks | C8: Platform Architecture | D8: Enterprise AI Platform Reference Architecture | E8: Standard architecture for enterprise AI platforms | F8: 계층별 아키텍처, 필수/선택 컴포넌트, 인터페이스, 배포모델, Security Layer | G8: High | H8: Not Started | J8: 24 | L8: Enterprise AI Platform
A9: A3-2 | B9: A3. Design Frameworks | C9: MLOps | D9: MLOps Reference Architecture | E9: End-to-end MLOps pipeline design | F9: Pipeline 구조, 6단계 프로세스, 도구 옵션, CI/CD 패턴, Monitoring Stack | G9: Medium | H9: Not Started | J9: 20 | L9: Enterprise AI Platform
A10: A3-3 | B10: A3. Design Frameworks | C10: Operating Model | D10: Operating Model Patterns | E10: Organization design patterns for AI CoE | F10: 3가지 조직 모델, 거버넌스 구조, 의사결정 권한, 적용조건, 전환경로 | G10: Medium | H10: Not Started | J10: 16 | L10: AI Operating Model
A11: A4-1 | B11: A4. Implementation Methodology | C11: RAG Design | D11: RAG System Design Methodology | E11: Comprehensive methodology for RAG system development | F11: Maturity Model, Chunking Strategy, Embedding 선정, Retrieval Strategy, Design Patterns | G11: High | H11: Not Started | J11: 20 | L11: AI Solution Accelerator
A12: A4-2 | B12: A4. Implementation Methodology | C12: Prompt Engineering | D12: Prompt Engineering Framework | E12: Systematic approach to prompt design and optimization | F12: 프롬프트 구조, Pattern Catalog, Few-shot 가이드, CoT 원칙, Optimization Process | G12: Medium | H12: Not Started | J12: 12 | L12: AI Solution Accelerator
A13: A4-3 | B13: A4. Implementation Methodology | C13: Model Governance | D13: Model Governance Methodology | E13: Lifecycle management for AI models | F13: Lifecycle 정의, Stage-gate 기준, Model Card 표준, Approval Workflow, Drift Detection | G13: Medium | H13: Not Started | J13: 16 | L13: AI Operating Model
A14: A5-1 | B14: A5. Measurement Frameworks | C14: ROI Model | D14: AI Project ROI Model | E14: Framework for calculating AI project returns | F14: 비용구조, 효과측정 방법, ROI 계산공식, Payback Period, 민감도 분석 | G14: Medium | H14: Not Started | J14: 12 | L14: AI Strategy & Readiness
A15: A5-2 | B15: A5. Measurement Frameworks | C15: Evaluation | D15: AI System Evaluation Framework | E15: Comprehensive evaluation methodology for AI systems | F15: 평가차원, 차원별 메트릭, Test Set 구성, Benchmark 프로토콜, Human Evaluation | G15: Medium | H15: Not Started | J15: 16 | L15: AI Solution Accelerator

Sheet B_Templates
A1: ID | B1: Category | C1: Sub-Category | D1: Asset Name | E1: Description | F1: Key Contents Summary | G1: Priority | H1: Status | I1: Owner | J1: Est. Hours | K1: Target Date | L1: Related Service Pack | M1: Notes
A2: B1-1 | B2: B1. Assessment Templates | C2: Maturity Assessment | D2: AI Maturity Assessment Questionnaire | E2: 100-150 questions for comprehensive maturity evaluation | F2: 차원별 질문, 5점 척도, 자동 스코어링, 시각화 차트, 벤치마크 비교 | G2: High | H2: Not Started | J2: 16 | L2: AI Strategy & Readiness
A3: B1-2 | B3: B1. Assessment Templates | C3: Interview Guides | D3: Interview Guide Set | E3: Structured interview guides for stakeholders | F3: 경영진/CIO/사업부장/실무자용 질문, Follow-up 가이드, 응답 기록 템플릿 | G3: High | H3: Not Started | J3: 12 | L3: AI Strategy & Readiness
A4: B1-3 | B4: B1. Assessment Templates | C4: Current State | D4: Current State Assessment Template | E4: Template for capturing current state inventory | F4: 시스템 인벤토리, 데이터 자산 평가, 기술 스택, 조직구조, Gap Analysis | G4: Medium | H4: Not Started | J4: 8 | L4: AI Strategy & Readiness
A5: B2-1 | B5: B2. Strategy Templates | C5: Use Case Canvas | D5: Use Case Canvas | E5: 1-page canvas for use case definition | F5: 8개 섹션, 작성 가이드, 예시 3-5개 | G5: High | H5: Not Started | J5: 6 | L5: AI Strategy & Readiness
A6: B2-2 | B6: B2. Strategy Templates | C6: Prioritization | D6: Use Case Prioritization Scorecard | E6: Scoring template for use case evaluation | F6: 평가기준, 가중치 설정, 자동 계산, 2x2 매트릭스, 우선순위 리스트 | G6: High | H6: Not Started | J6: 8 | L6: AI Strategy & Readiness
A7: B2-3 | B7: B2. Strategy Templates | C7: Roadmap | D7: AI Transformation Roadmap Template | E7: Visual roadmap template for 3-5 year transformation | F7: 분기별 타임라인, Swimlane, 마일스톤, 의존성, Wave 구분 | G7: High | H7: Not Started | J7: 8 | L7: AI Strategy & Readiness
A8: B2-4 | B8: B2. Strategy Templates | C8: Investment Plan | D8: Investment Plan & Budget Template | E8: Budget planning and allocation template | F8: 비용항목, 연도별/분기별 배분, Use case별 할당, ROI 계산 | G8: Medium | H8: Not Started | J8: 6 | L8: AI Strategy & Readiness
A9: B3-1 | B9: B3. Design Templates | C9: ADR | D9: Architecture Decision Record (ADR) | E9: Template for documenting architecture decisions | F9: Context, Decision, Alternatives, Consequences, Status | G9: High | H9: Not Started | J9: 4 | L9: Enterprise AI Platform
A10: B3-2 | B10: B3. Design Templates | C10: Tech Assessment | D10: Technology Stack Assessment Matrix | E10: Comparison matrix for technology evaluation | F10: 비교 기술/도구, 평가기준, 스코어링, 가중치 적용, 추천 결과 | G10: Medium | H10: Not Started | J10: 6 | L10: Enterprise AI Platform
A11: B3-3 | B11: B3. Design Templates | C11: Context Model | D11: Context Model Canvas | E11: Canvas for designing context management systems | F11: Semantic Layer, Entity/Relationship, Knowledge Source, Context Type, Retrieval Strategy | G11: High | H11: Not Started | J11: 8 | L11: Enterprise AI Platform
A12: B3-4 | B12: B3. Design Templates | C12: Agent Design | D12: Agent Design Canvas | E12: Canvas for agent specification | F12: Profile, Input/Output, Tool Inventory, Memory, Interaction Pattern, Success Metrics | G12: High | H12: Not Started | J12: 6 | L12: AI Solution Accelerator
A13: B3-5 | B13: B3. Design Templates | C13: API Spec | D13: API Specification Template | E13: Template for API documentation | F13: Endpoint 정의, Request/Response Schema, Authentication, Rate Limiting, Error Codes | G13: Medium | H13: Not Started | J13: 4 | L13: Enterprise AI Platform
... A34: B8-3 | B34: B8. Deliverable Templates | C34: Handover Package | D34: Handover Package Template | E34: Project handover checklist | F34: Project Summary, Deliverables Checklist, Code Repo, Documentation, Known Issues | G34: Medium | H34: Not Started | J34: 4 | L34: All

Sheet C_Playbooks
A1: ID | B1: Category | C1: Sub-Category | D1: Asset Name | E1: Description | F1: Key Contents Summary | G1: Priority | H1: Status | I1: Owner | J1: Est. Hours | K1: Target Date | L1: Related Service Pack | M1: Notes
A2: C1-1 | B2: C1. Project Playbooks | C2: Strategy & Readiness | D2: AI Strategy & Readiness Playbook | E2: 2-4 week playbook for strategy consulting | F2: Week-by-week Plan, Activity Guide, Deliverable Checklist, Red Flags, FAQ | G2: High | H2: Not Started | J2: 24 | L2: AI Strategy & Readiness
A3: C1-2 | B3: C1. Project Playbooks | C3: Operating Model | D3: AI Operating Model Playbook | E3: 4-8 week playbook for organization design | F3: 4 Phase 실행계획, Facilitation Guide, Stakeholder Engagement, Common Pitfalls | G3: Medium | H3: Not Started | J3: 20 | L3: AI Operating Model
A4: C1-3 | B4: C1. Project Playbooks | C4: Platform Design | D4: Enterprise AI Platform Playbook | E4: 8-12 week playbook for platform architecture | F4: 12주 상세계획, 5C Framework 적용가이드, Tech Selection, PoC Guide, Review Protocol | G4: High | H4: Not Started | J4: 32 | L4: Enterprise AI Platform | M4: IP 자산
A5: C1-4 | B5: C1. Project Playbooks | C5: Solution Accelerator | D5: AI Solution Accelerator Playbook | E5: 4-8 week sprint-based implementation playbook | F5: 8주 Sprint Plan, RAG 구축가이드, Agent 개발가이드, Evaluation 실행, Debugging | G5: High | H5: Not Started | J5: 24 | L5: AI Solution Accelerator
A6: C1-5 | B6: C1. Project Playbooks | C6: Capability Building | D6: AI Capability Building Playbook | E6: Program design and delivery playbook | F6: Program Design, Facilitation Tips, Hands-on Lab 운영, Assessment, Feedback Collection | G6: Low | H6: Not Started | J6: 12 | L6: AI Capability Building
A7: C1-6 | B7: C1. Project Playbooks | C7: Risk & Compliance | D7: AI Risk & Compliance Playbook | E7: 4-6 week risk and compliance playbook | F7: 6주 실행계획, Risk Workshop 가이드, Regulatory Research, Policy Drafting, Audit Prep | G7: Medium | H7: Not Started | J7: 16 | L7: AI Risk & Compliance
A8: C2-1 | B8: C2. Technical Guides | C8: Context Engineering | D8: Context Engineering Implementation Guide | E8: Step-by-step guide for context system implementation | F8: Semantic Model 설계, Knowledge Graph 구축, Context Retrieval 구현, QA, Code Examples | G8: High | H8: Not Started | J8: 32 | L8: Enterprise AI Platform | M8: IP 자산
A9: C2-2 | B9: C2. Technical Guides | C9: RAG Implementation | D9: RAG System Implementation Guide | E9: Comprehensive RAG system build guide | F9: Architecture Overview, Component별 구축, Optimization Techniques, Troubleshooting | G9: High | H9: Not Started | J9: 24 | L9: AI Solution Accelerator
A10: C2-3 | B10: C2. Technical Guides | C10: Agent Development | D10: Agent Development Guide | E10: Multi-agent system development guide | F10: Architecture Patterns, LangGraph/CrewAI 활용, Tool Integration, Memory 구현, Testing | G10: High | H10: Not Started | J10: 20 | L10: AI Solution Accelerator
A11: C2-4 | B11: C2. Technical Guides | C11: MLOps Setup | D11: MLOps Pipeline Setup Guide | E11: MLOps infrastructure setup guide | F11: Infrastructure Setup, Tool Stack 구성, Pipeline 구현, Monitoring, CI/CD | G11: Medium | H11: Not Started | J11: 16 | L11: Enterprise AI Platform
A12: C3-1 | B12: C3. Application Guides | C12: 5C Framework | D12: 5C Framework Application Guide | E12: Guide for applying 5C Framework | F12: When/How to apply, 각 C별 체크리스트, Integration Points, Success Indicators, Cases | G12: High | H12: Not Started | J12: 16 | L12: Enterprise AI Platform
A13: C3-2 | B13: C3. Application Guides | C13: Use Case Priority | D13: Use Case Prioritization Guide | E13: Workshop facilitation guide for prioritization | F13: Preparation, Workshop Process, Scoring, Facilitation Tips, Output Validation | G13: Medium | H13: Not Started | J13: 8 | L13: AI Strategy & Readiness
A14: C3-3 | B14: C3. Application Guides | C14: Risk Assessment | D14: Risk Assessment Execution Guide | E14: How to conduct risk assessment | F14: Prep Checklist, Interview/Workshop Protocol, Scoring Calibration, Heat Map, Report | G14: Medium | H14: Not Started | J14: 8 | L14: AI Risk & Compliance
A15: C4-1 | B15: C4. Quality Guides | C15: Peer Review | D15: Peer Review Guide | E15: Standards for peer review process | F15: Review 대상, Checklist, Process, Feedback 작성, Common Issues | G15: Medium | H15: Not Started | J15: 6 | L15: All
A16: C4-2 | B16: C4. Quality Guides | C16: QA Checklist | D16: Quality Assurance Checklist | E16: Comprehensive QA standards | F16: Phase별 QA 체크포인트, 산출물별 품질기준, Technical/Documentation Review | G16: Medium | H16: Not Started | J16: 8 | L16: All
A17: C5-1 | B17: C5. Sales Guides | C17: Sales Conversation | D17: Sales Conversation Guide | E17: Guide for discovery and sales conversations | F17: Discovery Questions, Pain Point Mapping, Objection Handling, Value Prop, Next Step | G17: High | H17: Not Started | J17: 12 | L17: All | M17: 영업 프로세스
A18: C5-2 | B18: C5. Sales Guides | C18: Proposal Development | D18: Proposal Development Guide | E18: How to write winning proposals | F18: 제안서 구조, Section별 작성가이드, Storytelling, Pricing 전략, Win Theme | G18: High | H18: Not Started | J18: 12 | L18: All | M18: 영업 프로세스

Sheet D_Knowledge
A1: ID | B1: Category | C1: Sub-Category | D1: Asset Name | E1: Description | F1: Key Contents Summary | G1: Priority | H1: Status | I1: Owner | J1: Est. Hours | K1: Target Date | L1: Related Service Pack | M1: Notes
A2: D1-1 | B2: D1. Case Studies | C2: Template | D2: Project Case Study Template | E2: Standard template for case study documentation | F2: Client Profile, Challenge, Approach, Solution, Results, Lessons Learned | G2: High | H2: Not Started | J2: 4 | L2: All
A3: D1-2 | B3: D1. Case Studies | C3: Financial Services | D3: Financial Services Case Studies | E3: Case studies from financial sector projects | F3: 금융권 AI 전환 사례, 규제 대응 사례, RAG/Agent 구현 사례 등 | G3: High | H3: Not Started | J3: 40 | L3: Multiple | M3: 최소 3-5개 축적
A4: D1-3 | B4: D1. Case Studies | C4: Telecom | D4: Telecom Case Studies | E4: Case studies from telecommunications sector | F4: 통신사 AI 플랫폼 구축, 대규모 시스템 통합 사례 등 | G4: Medium | H4: Not Started | J4: 32 | L4: Multiple | M4: 최소 2-3개
A5: D1-4 | B5: D1. Case Studies | C5: Manufacturing | D5: Manufacturing Case Studies | E5: Case studies from manufacturing sector | F5: 제조업 AI 활용 사례, 예지보전, 품질관리 등 | G5: Low | H5: Not Started | J5: 24 | L5: Multiple | M5: 선택적 축적
A6: D1-5 | B6: D1. Case Studies | C6: Public Sector | D6: Public Sector Case Studies | E6: Case studies from government/public sector | F6: 공공기관 AI 도입 사례, 컴플라이언스 중심 사례 | G6: Medium | H6: Not Started | J6: 24 | L6: Multiple | M6: 선택적 축적
A7: D2-1 | B7: D2. Best Practices | C7: Technical | D7: Technical Best Practices | E7: Collection of technical best practices | F7: RAG (20개), Agent (15개), MLOps (25개), Security (30개) | G7: High | H7: Not Started | J7: 40 | L7: All | M7: 지속 축적
A8: D2-2 | B8: D2. Best Practices | C8: Project Mgmt | D8: Project Management Best Practices | E8: PM best practices collection | F8: Stakeholder Mgmt, Risk Mgmt, Communication, Change Mgmt | G8: Medium | H8: Not Started | J8: 16 | L8: All
A9: D2-3 | B9: D2. Best Practices | C9: Consulting | D9: Consulting Best Practices | E9: Consulting delivery best practices | F9: Client Engagement, Workshop Facilitation, Presentation, Knowledge Transfer | G9: Medium | H9: Not Started | J9: 16 | L9: All
A10: D3-1 | B10: D3. Lessons Learned | C10: Template | D10: Lessons Learned Template | E10: Template for capturing lessons learned | F10: Project Context, What Worked, What Didnt, Root Cause, Recommendations | G10: Medium | H10: Not Started | J10: 3 | L10: All
A11: D3-2 | B11: D3. Lessons Learned | C11: Common Pitfalls | D11: Common Pitfalls Library | E11: Database of common mistakes and issues | F11: 기술선정, 스코핑, 데이터, 조직/정치, 일정/예산 실수들 | G11: Medium | H11: Not Started | J11: 24 | L11: All | M11: 지속 축적
A12: D4-1 | B12: D4. Reference Materials | C12: Tech Landscape | D12: Technology Landscape | E12: Comprehensive technology catalog | F12: LLM Platforms, Vector/Graph DB, MLOps Tools, Monitoring, Data Processing | G12: Medium | H12: Not Started | J12: 32 | L12: All | M12: 분기 업데이트
A13: D4-2 | B13: D4. Reference Materials | C13: Research Papers | D13: Research Paper Library | E13: Curated research paper collection | F13: RAG, Multi-agent, Prompt Engineering, Evaluation, AI Safety - 요약/인사이트 | G13: Low | H13: Not Started | J13: 40 | L13: All | M13: 지속 축적
A14: D4-3 | B14: D4. Reference Materials | C14: Industry Reports | D14: Industry Reports & Trends | E14: Industry report collection | F14: Gartner/Forrester, Anthropic/OpenAI, 학술컨퍼런스, 산업별 트렌드 | G14: Low | H14: Not Started | J14: 24 | L14: All | M14: 분기 업데이트

Sheet E_Sales
A1: ID | B1: Category | C1: Sub-Category | D1: Asset Name | E1: Description | F1: Key Contents Summary | G1: Priority | H1: Status | I1: Owner | J1: Est. Hours | K1: Target Date | L1: Related Service Pack | M1: Notes
A2: E1-1 | B2: E1. Service Materials | C2: Company Overview | D2: Company Overview Deck | E2: Master company introduction presentation | F2: Who We Are, What We Do, Differentiation, Approach, Cases, Team - 15-20 slides | G2: High | H2: Not Started | J2: 16 | L2: All
A3: E1-2 | B3: E1. Service Materials | C3: Strategy Service | D3: AI Strategy & Readiness Deck | E3: Service line deck for strategy consulting | F3: Overview, Value Prop, Approach, Deliverables, Timeline, Cases - 8-10 slides | G3: High | H3: Not Started | J3: 8 | L3: AI Strategy & Readiness
A4: E1-3 | B4: E1. Service Materials | C4: Operating Model | D4: AI Operating Model Deck | E4: Service line deck for operating model | F4: Overview, Value Prop, Approach, Deliverables, Timeline, Cases - 8-10 slides | G4: Medium | H4: Not Started | J4: 8 | L4: AI Operating Model
A5: E1-4 | B5: E1. Service Materials | C5: Platform Service | D5: Enterprise AI Platform Deck | E5: Service line deck for platform design | F5: Overview, Value Prop, 5C Framework, Approach, Deliverables, Cases - 10-12 slides | G5: High | H5: Not Started | J5: 12 | L5: Enterprise AI Platform | M5: IP 강조
A6: E1-5 | B6: E1. Service Materials | C6: Solution Service | D6: AI Solution Accelerator Deck | E6: Service line deck for solution implementation | F6: Overview, Value Prop, Approach, Deliverables, Timeline, Cases - 8-10 slides | G6: High | H6: Not Started | J6: 8 | L6: AI Solution Accelerator
A7: E1-6 | B7: E1. Service Materials | C7: Capability Service | D7: AI Capability Building Deck | E7: Service line deck for training/education | F7: Overview, Value Prop, Approach, Deliverables, Timeline, Cases - 8-10 slides | G7: Low | H7: Not Started | J7: 6 | L7: AI Capability Building
A8: E1-7 | B8: E1. Service Materials | C8: Risk Service | D8: AI Risk & Compliance Deck | E8: Service line deck for risk/compliance | F8: Overview, Value Prop, Approach, Deliverables, Timeline, Cases - 8-10 slides | G8: Medium | H8: Not Started | J8: 8 | L8: AI Risk & Compliance
A9: E1-8 | B9: E1. Service Materials | C9: Methodology | D9: Methodology Showcase Deck | E9: Presentation of core IP and methodologies | F9: 5C Framework 설명, Context Engineering 개요, 적용사례, 차별화 | G9: High | H9: Not Started | J9: 12 | L9: Enterprise AI Platform | M9: IP 자산
A10: E2-1 | B10: E2. Proposal Templates | C10: Master Proposal | D10: Master Proposal Template | E10: Comprehensive proposal template | F10: Cover, Executive Summary, Requirements, Approach, Deliverables, Timeline, Investment, Qualifications | G10: High | H10: Not Started | J10: 16 | L10: All
A11: E2-2 | B11: E2. Proposal Templates | C11: SOW | D11: Statement of Work (SOW) Template | E11: Standard SOW template | F11: Scope, Objectives, Deliverables, Assumptions, Roles, Timeline, Payment Terms | G11: High | H11: Not Started | J11: 8 | L11: All
A12: E2-3 | B12: E2. Proposal Templates | C12: Pricing | D12: Pricing Templates | E12: Pricing model templates | F12: Fixed Price, T&M, Retainer 모델, 서비스팩별 가격표, Add-ons, Discount Structure | G12: High | H12: Not Started | J12: 12 | L12: All | M12: 민감정보
A13: E3-1 | B13: E3. Marketing Content | C13: Thought Leadership | D13: Thought Leadership Articles | E13: Collection of articles and blog posts | F13: Enterprise AI 5원칙, Context Engineering, AI Governance 등 - 분기별 2-3개 | G13: Medium | H13: Not Started | J13: 40 | L13: All | M13: 지속 발행
A14: E3-2 | B14: E3. Marketing Content | C14: Webinars | D14: Webinar/Workshop Materials | E14: Webinar series materials | F14: AI Transformation 시작, Enterprise RAG 전략, AI 리스크 관리 - 1시간 각 | G14: Low | H14: Not Started | J14: 48 | L14: All | M14: 선택적
A15: E3-3 | B15: E3. Marketing Content | C15: White Papers | D15: White Papers | E15: In-depth white papers | F15: 5C Framework Deep-dive, Platform Architecture Guide, Governance Framework - 연 2-3개 | G15: Medium | H15: Not Started | J15: 80 | L15: Multiple | M15: 연간 계획

Sheet F_Operations
A1: ID | B1: Category | C1: Sub-Category | D1: Asset Name | E1: Description | F1: Key Contents Summary | G1: Priority | H1: Status | I1: Owner | J1: Est. Hours | K1: Target Date | L1: Related Service Pack | M1: Notes
A2: F1-1 | B2: F1. Project Management | C2: Lifecycle | D2: Project Lifecycle Standard | E2: Standard project lifecycle definition | F2: 5 Phases 정의, Phase별 목적/활동/산출물/Gate 기준 | G2: High | H2: Not Started | J2: 12 | L2: All
A3: F1-2 | B3: F1. Project Management | C3: Kickoff | D3: Project Kickoff Protocol | E3: Standard kickoff process | F3: Kickoff 전 준비, Meeting Agenda, Deck Template, 팀소개, Ground Rules | G3: Medium | H3: Not Started | J3: 8 | L3: All
A4: F1-3 | B4: F1. Project Management | C4: Status Reporting | D4: Status Reporting Process | E4: Reporting standards and cadence | F4: Weekly Meeting 형식, Reporting Frequency, Escalation Path, Dashboard | G4: Medium | H4: Not Started | J4: 6 | L4: All
A5: F2-1 | B5: F2. Quality Management | C5: Review Process | D5: Quality Review Process | E5: QA review process standards | F5: Review 시점, Reviewer 지정, Checklist, Feedback Loop, Approval | G5: High | H5: Not Started | J5: 8 | L5: All
A6: F2-2 | B6: F2. Quality Management | C6: Standards | D6: Deliverable Standards | E6: Quality standards for all deliverables | F6: 문서 품질기준, 코드 품질기준, 프레젠테이션 기준 | G6: Medium | H6: Not Started | J6: 12 | L6: All
A7: F3-1 | B7: F3. Knowledge Management | C7: Capture Process | D7: Knowledge Capture Process | E7: Process for capturing project learnings | F7: 프로젝트 종료 시 수행사항, Lessons Learned Session, 지식자산 업데이트 | G7: Medium | H7: Not Started | J7: 6 | L7: All
A8: F3-2 | B8: F3. Knowledge Management | C8: Repository | D8: Knowledge Repository Structure | E8: Standards for knowledge organization | F8: 폴더구조, 명명규칙, 접근권한, 버전관리, 검색 태그체계 | G8: High | H8: Not Started | J8: 8 | L8: All
A9: F3-3 | B9: F3. Knowledge Management | C9: Improvement | D9: Continuous Improvement Process | E9: Process for ongoing improvement | F9: 분기별 Review, 방법론 업데이트, 템플릿 개선, Best Practice 공유 | G9: Medium | H9: Not Started | J9: 6 | L9: All

Sheet G_People
A1: ID | B1: Category | C1: Sub-Category | D1: Asset Name | E1: Description | F1: Key Contents Summary | G1: Priority | H1: Status | I1: Owner | J1: Est. Hours | K1: Target Date | L1: Related Service Pack | M1: Notes
A2: G1-1 | B2: G1. Competency Framework | C2: Model | D2: Consultant Competency Model | E2: Comprehensive competency framework | F2: 3 Levels, 5 Competency Areas, 레벨별×영역별 매트릭스, 행동지표 | G2: High | H2: Not Started | J2: 20 | L2: All
A3: G1-2 | B3: G1. Competency Framework | C3: Roles | D3: Role Profiles | E3: Detailed role definitions | F3: Strategy/Architecture/Engineer/Data Scientist/Governance Consultant - 각 Role별 상세 | G3: Medium | H3: Not Started | J3: 16 | L3: All
A4: G2-1 | B4: G2. Hiring & Onboarding | C4: Hiring | D4: Hiring Guide | E4: Hiring process and standards | F4: Job Description 템플릿, Interview Questions (50개), 평가기준표, Case Interview | G4: Medium | H4: Not Started | J4: 16 | L4: All
A5: G2-2 | B5: G2. Hiring & Onboarding | C5: Onboarding | D5: Onboarding Program | E5: 8-week onboarding program | F5: Week 1-2: 방법론, Week 3-4: Shadow, Week 5-8: 참여, Buddy System, 평가 | G5: Medium | H5: Not Started | J5: 24 | L5: All
A6: G3-1 | B6: G3. Training | C6: Curriculum | D6: Internal Training Curriculum | E6: Complete training program | F6: 5 Modules: Consulting, AI/ML, Methodology, Tools, Advanced Topics | G6: High | H6: Not Started | J6: 80 | L6: All
A7: G3-2 | B7: G3. Training | C7: Development Paths | D7: Skill Development Paths | E7: Career progression learning paths | F7: Junior→Senior (12-24mo), Senior→Principal (24-36mo), 필수/선택 학습 | G7: Medium | H7: Not Started | J7: 12 | L7: All

Sheet H_Systems
A1: ID | B1: Category | C1: Sub-Category | D1: Asset Name | E1: Description | F1: Key Contents Summary | G1: Priority | H1: Status | I1: Owner | J1: Est. Hours | K1: Target Date | L1: Related Service Pack | M1: Notes
A2: H1-1 | B2: H1. Infrastructure | C2: Collaboration | D2: Collaboration Platform | E2: Setup for knowledge and collaboration tools | F2: Knowledge Repository (Notion/Confluence), File Storage, Version Control, Communication | G2: High | H2: Not Started | J2: 16 | L2: All | M2: Setup 필요
A3: H1-2 | B3: H1. Infrastructure | C3: Project Mgmt | D3: Project Management Tools | E3: PM tool configuration | F3: Task Management (Jira/Asana), Timeline, Time Tracking | G3: Medium | H3: Not Started | J3: 8 | L3: All | M3: Setup 필요
A4: H1-3 | B4: H1. Infrastructure | C4: CRM | D4: Proposal & CRM System | E4: Sales and proposal management | F4: CRM (HubSpot/Salesforce lite), Proposal Tool (PandaDoc), Contracting (DocuSign) | G4: Medium | H4: Not Started | J4: 12 | L4: All | M4: Setup 필요
A5: H2-1 | B5: H2. Template Management | C5: Library System | D5: Template Library System | E5: Central template management system | F5: 중앙 저장소, 카테고리 분류, 버전관리, 업데이트 프로세스, 접근권한 | G5: High | H5: Not Started | J5: 12 | L5: All
A6: H2-2 | B6: H2. Template Management | C6: Brand Assets | D6: Brand Assets | E6: Branding and design assets | F6: 로고, PPT 마스터템플릿, 색상팔레트, 폰트가이드, 아이콘 라이브러리 | G6: Medium | H6: Not Started | J6: 16 | L6: All | M6: 디자인 외주

Sheet ⚡ Implementation
A1: Phase | B1: Priority | C1: Asset ID | D1: Asset Name | E1: Category | F1: Description | G1: Est. Hours | H1: Dependencies | I1: Target Timeline | J1: Owner | K1: Status | L1: Notes
A2: Phase 1 | B2: Critical | C2: A1-1 | D2: 5C Framework | E2: Methodology | F2: Core IP - 5C Framework 완성 | G2: 40 | I2: Month 1-2 | K2: Not Started | L2: IP 자산
A3: Phase 1 | B3: Critical | C3: A1-2 | D3: Context Engineering Methodology | E3: Methodology | F3: Context Engineering 방법론 완성 | G3: 32 | H3: A1-1 | I3: Month 1-2 | K3: Not Started | L3: IP 자산
A4: Phase 1 | B4: Critical | C4: C2-1 | D4: Context Engineering Implementation Guide | E4: Playbook | F4: Context 시스템 구현 가이드 | G4: 32 | H4: A1-2 | I4: Month 2 | K4: Not Started
A5: Phase 1 | B5: Critical | C5: C1-3 | D5: Enterprise AI Platform Playbook | E5: Playbook | F5: Platform 설계 플레이북 | G5: 32 | H5: A1-1, A1-2 | I5: Month 2 | K5: Not Started
A6: Phase 1 | B6: Critical | C6: A4-1 | D6: RAG System Design Methodology | E6: Methodology | F6: RAG 시스템 설계 방법론 | G6: 20 | I6: Month 2 | K6: Not Started
A7: Phase 1 | B7: High | C7: D1-1 | D7: Project Case Study Template | E7: Knowledge | F7: Case study 템플릿 | G7: 4 | I7: Month 1 | K7: Not Started
A8: Phase 1 | B8: High | C8: D1-2 | D8: Financial Services Case Studies | E8: Knowledge | F8: Case study 2-3개 작성 | G8: 40 | H8: D1-1 | I8: Month 2-3 | K8: Not Started | L8: 실제 프로젝트 필요
A10: Phase 2 | B10: Critical | C10: B1-1 | D10: AI Maturity Assessment Questionnaire | E10: Template | F10: Maturity 평가 도구 | G10: 16 | H10: A2-1 | I10: Month 3 | K10: Not Started
A11: Phase 2 | B11: Critical | C11: B1-2 | D11: Interview Guide Set | E11: Template | F11: 인터뷰 가이드 | G11: 12 | I11: Month 3 | K11: Not Started
A12: Phase 2 | B12: Critical | C12: B2-1 | D12: Use Case Canvas | E12: Template | F12: Use case 정의 템플릿 | G12: 6 | H12: A2-2 | I12: Month 3 | K12: Not Started
A13: Phase 2 | B13: Critical | C13: B2-2 | D13: Use Case Prioritization Scorecard | E13: Template | F13: Prioritization 도구 | G13: 8 | H13: A2-2 | I13: Month 3 | K13: Not Started
A14: Phase 2 | B14: Critical | C14: A2-1 | D14: AI Maturity Model | E14: Methodology | F14: Maturity 평가 프레임워크 | G14: 16 | I14: Month 3 | K14: Not Started
A15: Phase 2 | B15: Critical | C15: A2-2 | D15: Use Case Prioritization Framework | E15: Methodology | F15: Use case 평가 프레임워크 | G15: 12 | I15: Month 3 | K15: Not Started
A16: Phase 2 | B16: Critical | C16: C2-2 | D16: RAG System Implementation Guide | E16: Playbook | F16: RAG 구현 가이드 | G16: 24 | H16: A4-1 | I16: Month 3 | K16: Not Started
A17: Phase 2 | B17: High | C17: C1-4 | D17: AI Solution Accelerator Playbook | E17: Playbook | F17: Solution 구현 플레이북 | G17: 24 | H17: A4-1, C2-2 | I17: Month 3-4 | K17: Not Started
A18: Phase 2 | B18: High | C18: E1-1 | D18: Company Overview Deck | E18: Sales | F18: 회사 소개 자료 | G18: 16 | I18: Month 3 | K18: Not Started
A19: Phase 2 | B19: High | C19: E2-1 | D19: Master Proposal Template | E19: Sales | F19: 제안서 템플릿 | G19: 16 | I19: Month 3 | K19: Not Started
A21: Phase 3 | B21: High | C21: A2-3 | D21: Risk Assessment Framework | E21: Methodology | F21: Risk 평가 프레임워크 | G21: 16 | I21: Month 4 | K21: Not Started
A22: Phase 3 | B22: High | C22: B6-1 | D22: Risk Register | E22: Template | F22: Risk 관리 템플릿 | G22: 6 | H22: A2-3 | I22: Month 4 | K22: Not Started
A23: Phase 3 | B23: High | C23: B6-2 | D23: Risk Assessment Worksheet | E23: Template | F23: Risk 평가 워크시트 | G23: 8 | H23: A2-3 | I23: Month 4 | K23: Not Started
A24: Phase 3 | B24: High | C24: A3-1 | D24: Enterprise AI Platform Reference Architecture | E24: Methodology | F24: Platform 아키텍처 | G24: 24 | H24: A1-1 | I24: Month 4-5 | K24: Not Started
A25: Phase 3 | B25: Medium | C25: A3-2 | D25: MLOps Reference Architecture | E25: Methodology | F25: MLOps 아키텍처 | G25: 20 | I25: Month 5 | K25: Not Started
A26: Phase 3 | B26: Medium | C26: C1-1 | D26: AI Strategy & Readiness Playbook | E26: Playbook | F26: Strategy 플레이북 | G26: 24 | H26: A2-1, A2-2 | I26: Month 4-5 | K26: Not Started
A27: Phase 3 | B27: Medium | C27: E1-4 | D27: Enterprise AI Platform Deck | E27: Sales | F27: Platform 서비스 소개 | G27: 12 | H27: A1-1 | I27: Month 5 | K27: Not Started
A29: Ongoing | B29: Medium | C29: D2-1 | D29: Technical Best Practices | E29: Knowledge | F29: Best practices 수집 | G29: 40 | I29: Continuous | K29: Not Started | L29: 지속 축적
A30: Ongoing | B30: Medium | C30: D3-2 | D30: Common Pitfalls Library | E30: Knowledge | F30: Pitfalls 데이터베이스 | G30: 24 | I30: Continuous | K30: Not Started | L30: 지속 축적
A31: Ongoing | B31: Low | C31: D4-1 | D31: Technology Landscape | E31: Knowledge | F31: 기술 카탈로그 | G31: 32 | I31: Quarterly Update | K31: Not Started | L31: 분기 업데이트
